lab2/alu.v
module alu (
    input [7:0] a,
    input [7:0] b,
    input [3:0] alu_sel,
    output reg[7:0] alu_result
);


always@(*)
begin
    case(alu_sel)
    4'b0000: alu_result= a + b;
    4'b0001: alu_result= a - b;
    4'b0010: alu_result= a * b; // don't enter number thatr results in 16 bit answer
    4'b0011: alu_result = (b != 0) ? (a / b) : 8'b0;
    4'b0100: alu_result= a & b;
    4'b0101: alu_result= a | b;
    4'b0110: alu_result= a ^ b;
    4'b0111: alu_result= ~(a & b) ;
    4'b1000: alu_result= ~(a | b);
    default: alu_result=8'bxxxxxxxx;
    endcase
end
    
endmodule

lab2/alu_tb.v
`timescale 1ns/1ps

module alu_tb;

reg [7:0] a,b;
reg [3:0] alu_sel;
wire[7:0] alu_result;

alu uut(
.a(a),
.b(b),
.alu_sel(alu_sel),
.alu_result(alu_result)
);

initial begin
    $dumpfile("alu.vcd");
    $dumpvars(0, uut);

    a=8'd20;
    b=8'd5;

    alu_sel=4'b0000;
    #10;

    alu_sel=4'b0001;
    #10;

    alu_sel=4'b0010;
    #10;
    alu_sel = 4'b0011; 
    #10; 

    alu_sel = 4'b0100; 
    #10; 
    
    alu_sel = 4'b0101; 
    #10; 
     
    alu_sel = 4'b0110; 
    #10; 
    
    alu_sel = 4'b0111; 
    #10; 
    
    alu_sel = 4'b1000;
    #10;
    $finish;
end
endmodule

lab2/alu.vcd
$date
	Fri Jun 26 09:22:47 2026
$end
$version
	Icarus Verilog
$end
$timescale
	1ps
$end
$scope module alu_tb $end
$scope module uut $end
$var wire 8 ! a [7:0] $end
$var wire 4 " alu_sel [3:0] $end
$var wire 8 # b [7:0] $end
$var reg 8 $ alu_result [7:0] $end
$upscope $end
$upscope $end
$enddefinitions $end
#0
$dumpvars
b11001 $
b101 #
b0 "
b10100 !
$end
#10000
b1111 $
b1 "
#20000
b1100100 $
b10 "
#30000
b100 $
b11 "
#40000
b100 "
#50000
b10101 $
b101 "
#60000
b10001 $
b110 "
#70000
b11111011 $
b111 "
#80000
b11101010 $
b1000 "
